typus/__init__.py
typus/core.py
typus/grammar.py
typus/backends/base.py
typus/backends/gbnf.py
typus/backends/regex.py
typus_dsl-0.3.2.dist-info/METADATA
typus_dsl-0.3.2.dist-info/WHEEL
typus_dsl-0.3.2.dist-info/RECORD
