Metadata-Version: 2.4
Name: typus-dsl
Version: 0.3.2
Summary: Add your description here
Author-email: Alejandro Piad <apiad@apiad.net>
Requires-Python: >=3.12
